sutil/__init__.py
sutil/base/Coin.py
sutil/base/Dataset.py
sutil/base/Experiment.py
sutil/base/__init__.py
sutil/metrics/ModelROC.py
sutil/metrics/MultiClassF1.py
sutil/metrics/__init__.py
sutil/models/LSTMModel.py
sutil/models/Model.py
sutil/models/RegularizedLinearRegression.py
sutil/models/RegularizedLogisticRegression.py
sutil/models/SklearnModel.py
sutil/models/__init__.py
sutil/neuralnet/NeuralNetworkClassifier.py
sutil/neuralnet/__init__.py
sutil/text/GramTokenizer.py
sutil/text/Num2Words.py
sutil/text/OneHotVectorizer.py
sutil/text/PhraseTokenizer.py
sutil/text/PreProcessor.py
sutil/text/StringJanitor.py
sutil/text/TFIDFVectorizer.py
sutil/text/TextDataset.py
sutil/text/TextVectorizer.py
sutil/text/__init__.py
soldai_utils-0.0.2.dist-info/LICENSE
soldai_utils-0.0.2.dist-info/METADATA
soldai_utils-0.0.2.dist-info/WHEEL
soldai_utils-0.0.2.dist-info/top_level.txt
soldai_utils-0.0.2.dist-info/RECORD
